references_parser/__init__.py
references_parser/__main__.py
references_parser/cli.py
references_parser/converters/__init__.py
references_parser/converters/url_converter.py
references_parser/models/__init__.py
references_parser/models/bibtex.py
references_parser/models/bibtex_ssau.py
references_parser/parsers/__init__.py
references_parser/parsers/ieee_parser.py
references_parser/parsers/ssau_parser.py
references_parser-1.2.1.dist-info/METADATA
references_parser-1.2.1.dist-info/WHEEL
references_parser-1.2.1.dist-info/entry_points.txt
references_parser-1.2.1.dist-info/top_level.txt
references_parser-1.2.1.dist-info/RECORD
