Metadata-Version: 2.1
Name: references-parser
Version: 1.2.1
Summary: Tool for parsing bibtex in ssau's format
Home-page: https://github.com/Banayaki/ReferencesParser
Author: Mukhin Artem
Author-email: artemmukhinssau@gmail.com
Classifier: Programming Language :: Python :: 3
Classifier: Topic :: Software Development :: Libraries :: Python Modules
Requires-Dist: beautifulsoup4 (==4.12.2)
Requires-Dist: bibtexparser (==1.4.0)
Requires-Dist: click (==8.1.3)
Requires-Dist: duckpy (==3.2.0)
Requires-Dist: Requests (==2.30.0)
Requires-Dist: pydantic (==1.10.2)
Requires-Dist: tqdm (==4.64.1)
